zyh_24_06_17/__init__.py
zyh_24_06_17/model_weights.joblib
zyh_24_06_17-5.0.0.dist-info/LICENSE.txt
zyh_24_06_17-5.0.0.dist-info/METADATA
zyh_24_06_17-5.0.0.dist-info/WHEEL
zyh_24_06_17-5.0.0.dist-info/top_level.txt
zyh_24_06_17-5.0.0.dist-info/RECORD
