Metadata-Version: 2.1
Name: zyh_24_06_17
Version: 5.0.0
Summary: A small example package
Home-page: 
Author: zyh
Author-email: zhuyihe@petail.com
Classifier: Programming Language :: Python :: 3
Classifier: License :: OSI Approved :: MIT License
Classifier: Operating System :: OS Independent
Requires-Python: >=3.6
License-File: LICENSE.txt
Requires-Dist: scikit-learn ==1.2.2
Requires-Dist: joblib ==1.4.2
Requires-Dist: numpy ==1.25.2
